hsm/__init__.py
hsm/hsm.py
hsm/kind.py
hsm/version.py
stateforward_hsm-0.1.1.dist-info/METADATA
stateforward_hsm-0.1.1.dist-info/WHEEL
stateforward_hsm-0.1.1.dist-info/licenses/LICENSE
stateforward_hsm-0.1.1.dist-info/RECORD
