Metadata-Version: 2.4
Name: stateforward.hsm
Version: 0.1.1
Summary: Hierarchical State Machine implementation for Python with asyncio support
Project-URL: Homepage, https://github.com/stateforward/hsm
Project-URL: Repository, https://github.com/stateforward/hsm-python
Project-URL: Documentation, https://github.com/stateforward/hsm-python
Project-URL: Issues, https://github.com/stateforward/hsm-python/issues
Author: Stateforward Team
License: MIT
License-File: LICENSE
Keywords: async,asyncio,finite-state-machine,hierarchical,hsm,state-machine
Classifier: Development Status :: 5 - Production/Stable
Classifier: Intended Audience :: Developers
Classifier: License :: OSI Approved :: MIT License
Classifier: Programming Language :: Python :: 3
Classifier: Programming Language :: Python :: 3.13
Classifier: Topic :: Software Development :: Libraries :: Python Modules
Classifier: Topic :: System :: Distributed Computing
Requires-Python: >=3.13
